mkdocs_badges/__init__.py
mkdocs_badges/assets/__init__.py
mkdocs_badges/assets/badge.css
mkdocs_badges/assets/badge.js
mkdocs_badges/assets/install_badge_data.json
mkdocs_badges/badge_html.py
mkdocs_badges/badge_replacer.py
mkdocs_badges/formatter.py
mkdocs_badges/install_badge.py
mkdocs_badges/parsed_badge.py
mkdocs_badges/parser.py
mkdocs_badges/plugin.py
mkdocs_badges/tag_badge.py
mkdocs_badges-0.5.2.dist-info/LICENSE
mkdocs_badges-0.5.2.dist-info/METADATA
mkdocs_badges-0.5.2.dist-info/WHEEL
mkdocs_badges-0.5.2.dist-info/entry_points.txt
mkdocs_badges-0.5.2.dist-info/RECORD
