Metadata-Version: 2.3
Name: mkdocs-badges
Version: 0.5.2
Summary: Add badges to your MkDocs page
License: MIT
Author: six-two
Author-email: pip@six-two.dev
Requires-Python: >=3.9
Classifier: License :: OSI Approved :: MIT License
Classifier: Programming Language :: Python :: 3
Classifier: Programming Language :: Python :: 3.9
Classifier: Programming Language :: Python :: 3.10
Classifier: Programming Language :: Python :: 3.11
Classifier: Programming Language :: Python :: 3.12
Classifier: Programming Language :: Python :: 3.13
Requires-Dist: mkdocs (>=1.5.0)
